odoo/addons/sm_carsharing_structure/__init__.py
odoo/addons/sm_carsharing_structure/__manifest__.py
odoo/addons/sm_carsharing_structure/models/__init__.py
odoo/addons/sm_carsharing_structure/models/models_cs_car.py
odoo/addons/sm_carsharing_structure/models/models_cs_car_service.py
odoo/addons/sm_carsharing_structure/models/models_cs_carconfig.py
odoo/addons/sm_carsharing_structure/models/models_cs_community.py
odoo/addons/sm_carsharing_structure/models/models_cs_production_unit.py
odoo/addons/sm_carsharing_structure/models/models_cs_task.py
odoo/addons/sm_carsharing_structure/models/models_cs_task_service_wizard.py
odoo/addons/sm_carsharing_structure/security/ir.model.access.csv
odoo/addons/sm_carsharing_structure/views/views.xml
odoo/addons/sm_carsharing_structure/views/views_cs_car.xml
odoo/addons/sm_carsharing_structure/views/views_cs_car_service.xml
odoo/addons/sm_carsharing_structure/views/views_cs_carconfig.xml
odoo/addons/sm_carsharing_structure/views/views_cs_community.xml
odoo/addons/sm_carsharing_structure/views/views_cs_production_unit.xml
odoo/addons/sm_carsharing_structure/views/views_cs_task.xml
odoo/addons/sm_carsharing_structure/views/views_cs_task_wizard.xml
odoo11_addon_sm_carsharing_structure-11.0.0.0.2.dist-info/METADATA
odoo11_addon_sm_carsharing_structure-11.0.0.0.2.dist-info/WHEEL
odoo11_addon_sm_carsharing_structure-11.0.0.0.2.dist-info/top_level.txt
odoo11_addon_sm_carsharing_structure-11.0.0.0.2.dist-info/RECORD
